LICENSE
MANIFEST.in
README.md
setup.py
buff/__init__.py
buff/bin.py
buff/buff.py
buff/test.py
buff.egg-info/PKG-INFO
buff.egg-info/SOURCES.txt
buff.egg-info/dependency_links.txt
buff.egg-info/top_level.txt